{"errors":[],"warnings":[],"namedChunkGroups":{"app":{"chunks":[6,2],"assets":["webpack-runtime-5915c3138c8cbeb4171a.js","webpack-runtime-5915c3138c8cbeb4171a.js.map","app-fe53bc9c63af192a2286.js","app-fe53bc9c63af192a2286.js.map"],"children":{},"childAssets":{}},"component---src-pages-404-js":{"chunks":[0,1,3],"assets":["styles.21843348e9623e1fa356.css","styles-85f55d0cdc44cbeaa26f.js","styles-85f55d0cdc44cbeaa26f.js.map","1-02acbea760ecd74d4e05.js","1-02acbea760ecd74d4e05.js.map","component---src-pages-404-js-a8ea7c58b6274b201087.js","component---src-pages-404-js-a8ea7c58b6274b201087.js.map"],"children":{},"childAssets":{}},"component---src-pages-index-js":{"chunks":[0,1,7,4],"assets":["styles.21843348e9623e1fa356.css","styles-85f55d0cdc44cbeaa26f.js","styles-85f55d0cdc44cbeaa26f.js.map","1-02acbea760ecd74d4e05.js","1-02acbea760ecd74d4e05.js.map","7-c28d065eced2a7f27e8d.js","7-c28d065eced2a7f27e8d.js.map","component---src-pages-index-js-5696645b8fb4ab854de3.js","component---src-pages-index-js-5696645b8fb4ab854de3.js.map"],"children":{},"childAssets":{}},"pages-manifest":{"chunks":[5],"assets":["pages-manifest-f772c2687954ba938339.js","pages-manifest-f772c2687954ba938339.js.map"],"children":{},"childAssets":{}}},"assetsByChunkName":{"app":["webpack-runtime-5915c3138c8cbeb4171a.js","app-fe53bc9c63af192a2286.js"],"component---src-pages-404-js":["styles.21843348e9623e1fa356.css","styles-85f55d0cdc44cbeaa26f.js","1-02acbea760ecd74d4e05.js","component---src-pages-404-js-a8ea7c58b6274b201087.js"],"component---src-pages-index-js":["styles.21843348e9623e1fa356.css","styles-85f55d0cdc44cbeaa26f.js","1-02acbea760ecd74d4e05.js","7-c28d065eced2a7f27e8d.js","component---src-pages-index-js-5696645b8fb4ab854de3.js"],"pages-manifest":["pages-manifest-f772c2687954ba938339.js"]}}